XoxoDay/__init__.py
XoxoDay/exception.py
XoxoDay/serializer.py
XoxoDay/helper/__init__.py
XoxoDay/helper/token.py
XoxoDay/service/__init__.py
XoxoDay/service/http_service.py
XoxoDay/service/placeOrder.json
XoxoDay/service/token_service.py
XoxoDay/service/voucher.json
XoxoDay/service/xoxoday_service.py
XoxoDay-0.0.31.dist-info/LICENSE
XoxoDay-0.0.31.dist-info/METADATA
XoxoDay-0.0.31.dist-info/WHEEL
XoxoDay-0.0.31.dist-info/top_level.txt
XoxoDay-0.0.31.dist-info/RECORD
