Metadata-Version: 2.1
Name: XoxoDay
Version: 0.0.31
Summary: XoxoDay Api Client For Python
Home-page: https://github.com/blueromans/XoxoDay.git
Author: Yaşar Özyurt
Author-email: blueromans@gmail.com
Project-URL: Bug Tracker, https://github.com/blueromans/XoxoDay/issues
Classifier: Programming Language :: Python :: 3
Classifier: License :: OSI Approved :: MIT License
Classifier: Operating System :: OS Independent
Requires-Python: >=3.6
License-File: LICENSE
Requires-Dist: requests
Requires-Dist: python-dotenv
